BasicReturns/__init__.py
BasicReturns/main.py
BasicReturns/py.typed
basicreturns-0.1.2.dist-info/licenses/LICENSE
basicreturns-0.1.2.dist-info/METADATA
basicreturns-0.1.2.dist-info/WHEEL
basicreturns-0.1.2.dist-info/top_level.txt
basicreturns-0.1.2.dist-info/RECORD
