Metadata-Version: 2.4
Name: BasicReturns
Version: 0.1.2
Summary: Standardizes function return values across Python applications to enhance code consistency, readability, and maintainability.
Author-email: Dev2Forge <support@dev2forge.software>
Maintainer-email: tutosrive <tutosriveorg@gmail.com>
License-Expression: MIT
Project-URL: Homepage, https://pypi.org/project/BasicReturns/
Project-URL: Repository, https://github.com/Dev2Forge/BasicReturns
Project-URL: Issues, https://github.com/Dev2Forge/BasicReturns/issues
Project-URL: Source, https://github.com/Dev2Forge/BasicReturns
Project-URL: Documentation, https://github.com/Dev2Forge/BasicReturns#readme
Keywords: unified-returns,consistent-returns,error-handling,python-patterns,function-returns,api-responses,dataclasses,type-safety,developer-tools,code-quality
Classifier: Development Status :: 4 - Beta
Classifier: Intended Audience :: Developers
Classifier: Topic :: Software Development :: Libraries :: Python Modules
Classifier: Topic :: Software Development :: Quality Assurance
Classifier: Programming Language :: Python :: 3
Classifier: Programming Language :: Python :: 3.8
Classifier: Programming Language :: Python :: 3.9
Classifier: Programming Language :: Python :: 3.10
Classifier: Programming Language :: Python :: 3.11
Classifier: Programming Language :: Python :: 3.12
Classifier: Operating System :: OS Independent
Classifier: Typing :: Typed
Classifier: Environment :: Console
Requires-Python: >=3.8
License-File: LICENSE
Requires-Dist: pydantic==2.12.5
Dynamic: license-file
